{
  "id": "0c385765-35cf-4d8e-bc0a-f8296b205ad3",
  "prevId": "53051416-3357-4bb6-8093-25471a8ca34f",
  "version": "7",
  "dialect": "postgresql",
  "tables": {
    "public.tickets": {
      "name": "tickets",
      "schema": "",
      "columns": {
        "id": {
          "name": "id",
          "type": "integer",
          "primaryKey": true,
          "notNull": true,
          "identity": {
            "type": "always",
            "name": "tickets_id_seq",
            "schema": "public",
            "increment": "1",
            "startWith": "1",
            "minValue": "1",
            "maxValue": "2147483647",
            "cache": "1",
            "cycle": false
          }
        },
        "title": {
          "name": "title",
          "type": "varchar(200)",
          "primaryKey": false,
          "notNull": true
        },
        "price": {
          "name": "price",
          "type": "numeric",
          "primaryKey": false,
          "notNull": true,
          "default": "'0.00'"
        },
        "version": {
          "name": "version",
          "type": "integer",
          "primaryKey": false,
          "notNull": true,
          "default": "nextval('ticket_version_seq')"
        },
        "userId": {
          "name": "userId",
          "type": "integer",
          "primaryKey": false,
          "notNull": true
        },
        "lock": {
          "name": "lock",
          "type": "boolean",
          "primaryKey": false,
          "notNull": true,
          "default": false
        },
        "createdAt": {
          "name": "createdAt",
          "type": "timestamp",
          "primaryKey": false,
          "notNull": false,
          "default": "now()"
        }
      },
      "indexes": {},
      "foreignKeys": {},
      "compositePrimaryKeys": {},
      "uniqueConstraints": {},
      "policies": {},
      "checkConstraints": {},
      "isRLSEnabled": false
    }
  },
  "enums": {},
  "schemas": {},
  "sequences": {},
  "roles": {},
  "policies": {},
  "views": {},
  "_meta": {
    "columns": {},
    "schemas": {},
    "tables": {}
  }
}
